rfgrade
