Metadata-Version: 1.0
Name: rfgrade
Version: 1.2
Summary: grader for rf
Home-page: UNKNOWN
Author: refactored
Author-email: refactored@colaberry.com
License: UNKNOWN
Platform: UNKNOWN
